anda/__init__.py
anda/concs.py
anda/gr.py
anda/textnet.py
anda/data/morpheus_by_lemma.json
anda/data/morpheus_dict.json
anda-0.0.8.dist-info/LICENSE.md
anda-0.0.8.dist-info/METADATA
anda-0.0.8.dist-info/WHEEL
anda-0.0.8.dist-info/top_level.txt
anda-0.0.8.dist-info/RECORD
