Metadata-Version: 2.1
Name: anda
Version: 0.0.8
Summary: A package collecting various functions to work with ancient Mediterranean datasets (textual, spatial, etc.)
Home-page: https://github.com/sdam-au/anda
Author: Vojtech Kase
Author-email: vojtech.kase@gmail.com
License: UNKNOWN
Platform: UNKNOWN
Classifier: Programming Language :: Python :: 3
Classifier: License :: CC0 1.0 Universal (CC0 1.0) Public Domain Dedication
Classifier: Operating System :: OS Independent
Requires-Python: >=3.4
